fast_hard/__init__.py
fast_hard/cli.py
fast_hard/templates/__init__.py
fast_hard/templates/mongodb.py
fast_hard/templates/mysql.py
fast_hard/templates/postgresql.py
fast_hard/templates/sqlite.py
fast_hard/utils/__init__.py
fast_hard/utils/project_initializer.py
fast_hard-0.1.3.dist-info/LICENSE
fast_hard-0.1.3.dist-info/METADATA
fast_hard-0.1.3.dist-info/WHEEL
fast_hard-0.1.3.dist-info/entry_points.txt
fast_hard-0.1.3.dist-info/top_level.txt
fast_hard-0.1.3.dist-info/RECORD
