Metadata-Version: 2.2
Name: fast-hard
Version: 0.1.3
Summary: Um pacote para gerar projetos FastAPI com estrutura básica.
Home-page: https://github.com/seu-usuario/fast_hard
Author: Felipe Hardmann
Author-email: fashardmann@gmail.com
Classifier: Programming Language :: Python :: 3
Classifier: License :: OSI Approved :: MIT License
Classifier: Operating System :: OS Independent
Requires-Python: >=3.6
License-File: LICENSE
Requires-Dist: click
Dynamic: author
Dynamic: author-email
Dynamic: classifier
Dynamic: description
Dynamic: description-content-type
Dynamic: home-page
Dynamic: requires-dist
Dynamic: requires-python
Dynamic: summary
